nbdefense/__init__.py
nbdefense/_version.py
nbdefense/cli.py
nbdefense/codebase.py
nbdefense/constants.py
nbdefense/dependencies.py
nbdefense/errors.py
nbdefense/issues.py
nbdefense/nbdefense.py
nbdefense/notebook.py
nbdefense/plugins/__init__.py
nbdefense/plugins/cve/cve_dependency_file_plugin.py
nbdefense/plugins/cve/cve_notebooks_plugin.py
nbdefense/plugins/cve/cve_plugin.py
nbdefense/plugins/licenses/license_plugin.py
nbdefense/plugins/licenses/license_plugin_settings.py
nbdefense/plugins/licenses/licenses_dependency_file_plugin.py
nbdefense/plugins/licenses/licenses_notebooks_plugin.py
nbdefense/plugins/pii.py
nbdefense/plugins/plugin.py
nbdefense/plugins/secrets.py
nbdefense/reports.py
nbdefense/settings.py
nbdefense/templates/errors.html
nbdefense/templates/files-scanned-dialog.html
nbdefense/templates/footer.html
nbdefense/templates/header.html
nbdefense/templates/icons/alert-icon-critical.svg
nbdefense/templates/icons/alert-icon-high.svg
nbdefense/templates/icons/alert-icon-low.svg
nbdefense/templates/icons/alert-icon-medium.svg
nbdefense/templates/icons/header-github.svg
nbdefense/templates/icons/x.svg
nbdefense/templates/issue-codes/dependency-file.html
nbdefense/templates/issue-codes/license-not-found-dep-file.html
nbdefense/templates/issue-codes/pii-found.html
nbdefense/templates/issue-codes/secrets.html
nbdefense/templates/issue-codes/unapproved-license-dep-file.html
nbdefense/templates/issue-codes/vulnerable-dependency-dep-file.html
nbdefense/templates/issue.html
nbdefense/templates/issues.html
nbdefense/templates/navbar.html
nbdefense/templates/no-issues.html
nbdefense/templates/report.html
nbdefense/templates/scripts.html
nbdefense/templates/summary-card.html
nbdefense/templating.py
nbdefense/tools.py
nbdefense/utils.py
nbdefense-1.0.5.dist-info/LICENSE
nbdefense-1.0.5.dist-info/METADATA
nbdefense-1.0.5.dist-info/WHEEL
nbdefense-1.0.5.dist-info/entry_points.txt
nbdefense-1.0.5.dist-info/RECORD
