Metadata-Version: 2.1
Name: nbdefense
Version: 1.0.5
Summary: NB Defense CLI and SDK
License: Apache-2.0
Author: ProtectAI
Author-email: community@protectai.com
Requires-Python: >=3.8,<3.11
Classifier: License :: OSI Approved :: Apache Software License
Classifier: Programming Language :: Python :: 3
Classifier: Programming Language :: Python :: 3.8
Classifier: Programming Language :: Python :: 3.9
Classifier: Programming Language :: Python :: 3.10
Requires-Dist: click (>=8.1.3,<9.0.0)
Requires-Dist: detect-secrets (==1.4.0)
Requires-Dist: jinja2 (>=3.1.2,<4.0.0)
Requires-Dist: nbconvert (==7.0.0)
Requires-Dist: nbformat (==5.6.1)
Requires-Dist: pandas (>=1.3.5,<2.0.0)
Requires-Dist: presidio_analyzer (==2.2.29)
Requires-Dist: requests (==2.32.2)
Requires-Dist: requirements-parser (==0.5.0)
Requires-Dist: rich (==12.6.0)
Requires-Dist: tomlkit (==0.11.6)
Requires-Dist: tqdm (==4.66.3)
